circuitdb/2_2_every_every
circuitdb/2_2_id-not-and-or_id-not-and-or
circuitdb/2_2_id-not-and-xor_and
circuitdb/3_1_every_every
circuitdb/3_1_id-not-and-or_id-not-and-or
circuitdb/3_1_id-not-and-xor_and
circuitdb/__init__.py
circuitdb/circuitdb.py
circuitdb-2.0.0.dist-info/LICENSE
circuitdb-2.0.0.dist-info/METADATA
circuitdb-2.0.0.dist-info/WHEEL
circuitdb-2.0.0.dist-info/top_level.txt
circuitdb-2.0.0.dist-info/RECORD
